{
  "RES_TIME": {
    "precision_mean": 0.569,
    "recall_mean": 1.0,
    "precision_std": 0.173,
    "recall_std": 0.0,
    "mhd_pos_mean": 0.969,
    "mhd_pos_std": 0.49,
    "mhd_false_mean": 0.765,
    "mhd_false_std": 0.222
  },
  "CPU": {
    "precision_mean": 0.831,
    "recall_mean": 1.0,
    "precision_std": 0.031,
    "recall_std": 0.0,
    "mhd_pos_mean": 0.0,
    "mhd_pos_std": 0.0,
    "mhd_false_mean": 1.711,
    "mhd_false_std": 0.244
  },
  "MEM": {
    "precision_mean": 0.909,
    "recall_mean": 1.0,
    "precision_std": 0.0,
    "recall_std": 0.0,
    "mhd_pos_mean": 0.0,
    "mhd_pos_std": 0.0,
    "mhd_false_mean": 0.333,
    "mhd_false_std": 0.0
  }
}